uc.v
`timescale 1 ns / 10 ps
//module cd(input wire [2:0] multiplicador, input wire [2:0] multiplicando, input wire Carga_A, Carga_QM, Desplaza_AQ, Reset_A, Resta, clk, reset, output wire q0, q_menos1, output wire [5:0] result);

module uc(input wire q0, reset, clk, q_menos1, output wire Carga_A, Carga_QM, Desplaza_AQ, Reset_A, Resta, Fin);

  reg [2:0] state, nextstate; //Variables para los estados actual y siguiente
                              //Tres bits son suficientes para los siete estados
  //Codificación de los estados
  parameter S0 = 3'b000; //declaracion de constantes que representan estados
  parameter S1 = 3'b001;
  parameter S2 = 3'b010;
  parameter S3 = 3'b011;
  parameter S4 = 3'b100;
  parameter S5 = 3'b101;
  parameter S6 = 3'b110;
  parameter S7 = 3'b111;

  // Registro de estado, cambia en cada flanco ciclo de reloj por el nuevo estado o
  // se inicia en caso de flanco de subida de reset al estado inicial

  always @ (posedge clk, posedge reset)
    if (reset)
    state <= S0;
    else
    state <= nextstate;

  //Función de Transición
  always @(*) // (*) significa cualquier cambio en alguna variable del bloque
    case (state)
    S0: nextstate = S1;
    S1: nextstate = S2;
    S2: nextstate = S3;
    S3: nextstate = S4;
    S4: nextstate = S5;
    S5: nextstate = S6;
    S6: nextstate = S7;
    S7: nextstate = S7;
    default: nextstate = S0;
  endcase

  // Función de Salida
  assign Carga_A = ((q0 & !(q_menos1)) &((state == S1)|(state == S3)|(state == S5)))? 1:0;
  assign Carga_QM = (state == S0)? 1:0; //a 1 si el estado es S0
  assign Desplaza_AQ = ((state == S2)|(state == S4)|(state == S6))? 1:0;
  assign Reset_A = (state == S0)? 1:0;
  assign Resta = ((q0 & !(q_menos1)) & ((state == S1)|(state == S3)|(state == S5)))? 1:0;
  //assign reset = (state == S0)? 1:0;
  assign Fin = (state == S7)? 1:0;

endmodule

  // Cuando tengamos que hacer la función de la salida, cuando desplazar, assign desplazamiento, cuando estemos en el estado s4
  // cuando estemos en tal s4 s2 y s6 desplazamiento
  // Sumar y cargar, las dos cosas. Voy a sumar siempre. Bueno si la señal es 10 restamos, si no sumamos
  //10 resta
  //01 suma

// -Wall en compilación

componentes.v
`timescale 1 ns / 10 ps


// A y M
module registro6 (input wire [5:0] entrada, input wire bit_en_desp, input wire Carga, Desplaza, clk, reset, output wire [5:0] salida);
  wire enable; 

  assign enable = Carga | Desplaza; //Si se carga o desplaza se habilitan en modificación los biestables

  cdaff ff0(Carga, entrada[0], salida[1], clk, reset, enable, salida[0]);
  cdaff ff1(Carga, entrada[1], salida[2], clk, reset, enable, salida[1]);
  cdaff ff2(Carga, entrada[2], salida[3], clk, reset, enable, salida[2]);
  cdaff ff3(Carga, entrada[3], salida[4], clk, reset, enable, salida[3]); 
  cdaff ff4(Carga, entrada[4], salida[5], clk, reset, enable, salida[4]); 
  cdaff ff5(Carga, entrada[5], bit_en_desp, clk, reset, enable, salida[5]); //entra un bit en el desplaz
endmodule

// M con 2 desp
module registro6_2desp (input wire [5:0] entrada, input wire [1:0] bit_en_desp, input wire Carga, Desplaza, clk, reset, output wire [5:0] salida);
  wire enable; 

  assign enable = Carga | Desplaza; //Si se carga o desplaza se habilitan en modificación los biestables

  cdaff ff0(Carga, entrada[0], salida[2], clk, reset, enable, salida[0]);
  cdaff ff1(Carga, entrada[1], salida[3], clk, reset, enable, salida[1]);
  cdaff ff2(Carga, entrada[2], salida[4], clk, reset, enable, salida[2]);
  cdaff ff3(Carga, entrada[3], salida[5], clk, reset, enable, salida[3]); 
  cdaff ff4(Carga, entrada[4], bit_en_desp[0], clk, reset, enable, salida[4]); 
  cdaff ff5(Carga, entrada[5], bit_en_desp[1], clk, reset, enable, salida[5]); //entra un bit en el desplaz
endmodule

// Q
module registro5 (input wire [4:0] entrada, input wire bit_en_desp, input wire Carga, Desplaza, clk, reset, output wire [4:0] salida);
  wire enable; 

  assign enable = Carga | Desplaza; //Si se carga o desplaza se habilitan en modificación los biestables

  cdaff ff0(Carga, entrada[0], salida[1], clk, reset, enable, salida[0]);
  cdaff ff1(Carga, entrada[1], salida[2], clk, reset, enable, salida[1]);
  cdaff ff2(Carga, entrada[2], salida[3], clk, reset, enable, salida[2]);
  cdaff ff3(Carga, entrada[3], salida[4], clk, reset, enable, salida[3]); 
  cdaff ff4(Carga, entrada[4], bit_en_desp, clk, reset, enable, salida[4]); //entra un bit en el desplaz
endmodule


// Podría ser A o M
// La línea de Carga indica que se va a asignar un nuevo valor al registro que viene por "entrada"
// La línea de Desplaza indica que se va a desplazar el contenido del registro. El bit más significativo se completa con la entrada "bit_en_desp"
module registro4 (input wire [3:0] entrada, input wire bit_en_desp, input wire Carga, Desplaza, clk, reset, output wire [3:0] salida);
  wire enable; 

  assign enable = Carga | Desplaza; //Si se carga o desplaza se habilitan en modificación los biestables

  cdaff ff0(Carga, entrada[0], salida[1], clk, reset, enable, salida[0]);
  cdaff ff1(Carga, entrada[1], salida[2], clk, reset, enable, salida[1]);
  cdaff ff2(Carga, entrada[2], salida[3], clk, reset, enable, salida[2]);
  cdaff ff3(Carga, entrada[3], bit_en_desp, clk, reset, enable, salida[3]); //entra un bit en el desplaz
endmodule

module registro4_2desp (input wire [3:0] entrada, input wire [1:0] bit_en_desp, input wire Carga, Desplaza, clk, reset, output wire [3:0] salida);
  wire enable; 

  assign enable = Carga | Desplaza; //Si se carga o desplaza se habilitan en modificación los biestables

  cdaff ff0(Carga, entrada[0], salida[2], clk, reset, enable, salida[0]);
  cdaff ff1(Carga, entrada[1], salida[3], clk, reset, enable, salida[1]);
  cdaff ff2(Carga, entrada[2], bit_en_desp[0], clk, reset, enable, salida[2]);
  cdaff ff3(Carga, entrada[3], bit_en_desp[1], clk, reset, enable, salida[3]); //entra un bit en el desplaz
endmodule

// Registro de 3 bits, soporta Carga de entrada, reseteo y desplazamiento aritmético o lógico
// La línea de Carga indica que se va a asignar un nuevo valor al registro que viene por "entrada"
// La línea de Desplaza indica que se va a desplazar el contenido del registro. El bit más significativo se completa con la entrada "bit_en_desp"
module registro3 (input wire [2:0] entrada, input wire bit_en_desp, input wire Carga, Desplaza, clk, reset, output wire [2:0] salida);
  wire enable;
  
  assign enable = Carga | Desplaza; //Si se carga o desplaza se habilitan en modificación los biestables

  cdaff ff0(Carga, entrada[0], salida[1], clk, reset, enable, salida[0]);
  cdaff ff1(Carga, entrada[1], salida[2], clk, reset, enable, salida[1]);
  cdaff ff2(Carga, entrada[2], bit_en_desp, clk, reset, enable, salida[2]); //entra un bit en el desplaz
endmodule

//Biestable con entrada de mux para aceptar dos entradas posibles
module cdaff (input wire selc_d, inp_c, inp_d, clk, reset, carga, output wire salida);
  wire inp;
  
  ffdc ff0(clk, reset, carga, inp, salida);
  mux2_1_i1 mux0(inp, inp_d, inp_c, selc_d);  // ah tengo que desplazar
endmodule

//Mux de dos entradas de 1 bit realizado a partir de puertas 
module mux2_1_i1(output wire out, input wire a, b, s);
  //Declaración de conexiones internas
  wire  s_n, sa, sb;     
  //Instancias de puertas y sus conexiones
  not inv1 (s_n, s);
  and and1 (sa, a, s_n);
  and and2 (sb, b, s);
  or or1 (out, sa, sb);
endmodule

//Mux de dos entradas para elegir M2 o M
module mux2_1_M2(output reg[5:0] out, input wire[5:0] a, b, input wire s);
  always @(s,a,b)
    if (!s)
      out = a;
    else
      out = b;
endmodule

module ffdc #(parameter retardo = 0)(input wire clk, reset, carga, d, output reg q);
  //reset asíncrono, carga síncrona
  always @(posedge clk, posedge reset)
    if (reset)
      q <= #retardo 1'b0; //asignación no bloqueante q=0
    else
      if (carga)
        q <= #retardo d; //asignación no bloqueante q=d
endmodule

// Sumador/Restador de 4 bits
module sum_resta4(output wire[3:0] S, output wire c_out, input wire[3:0] A, input wire[3:0] B, input wire resta);
  assign {c_out, S} = (resta == 1) ? A - B + 0 : A + B + 0;
endmodule

// Sumador/Restador de 5 bits
module sum_resta5(output wire[4:0] S, output wire c_out, input wire[4:0] A, input wire[4:0] B, input wire resta);
  assign {c_out, S} = (resta == 1) ? A - B + 0 : A + B + 0;
endmodule

// Sumador/Restador de 6 bits
module sum_resta6(output wire[5:0] S, output wire c_out, input wire[5:0] A, input wire[5:0] B, input wire resta);
  assign {c_out, S} = (resta == 1) ? A - B + 0 : A + B + 0;
endmodule

cd.v
`timescale 1 ns / 10 ps
// module registro4 (input wire [3:0] entrada, input wire bit_en_desp, input wire Carga, Desplaza, clk, reset, output wire [3:0] salida);
// module registro3 (input wire [2:0] entrada, input wire bit_en_desp, input wire Carga, Desplaza, clk, reset, output wire [2:0] salida);
// module sum_resta4(output wire[3:0] S, output wire c_out, input wire[3:0] A, input wire[3:0] B, input wire resta);
// module ffdc #(parameter retardo = 0)(input wire clk, reset, carga, d, output reg q);

module cd(input wire [2:0] multiplicador, input wire [2:0] multiplicando, input wire Carga_A, Carga_QM, Desplaza_AQ, Reset_A, Resta, clk, reset, output wire q0, q_menos1, output wire [5:0] result);

  wire [3:0] salida_sum, salida_M, salida_A;
  wire [2:0] salida_Q;
  wire reset_qmenos1, carga_qmenos1, c_sumout;
  registro4 M({multiplicando[2],multiplicando}, 1'b0, Carga_QM, 1'b0, clk, reset, salida_M);
  registro4 A(salida_sum, salida_A[3], Carga_A, Desplaza_AQ, clk, Reset_A, salida_A);
  registro3 Q(multiplicador, salida_A[0], Carga_QM, Desplaza_AQ, clk, reset, salida_Q); // Necesitamos pegarle un biestable llamado q-1
  sum_resta4 sumador(salida_sum, c_sumout, salida_A, salida_M, Resta);
  ffdc bq_menos1(clk, reset_qmenos1, Carga_QM, carga_qmenos1, q_menos1);  // Flip flop mas sencillo

  assign q0 = salida_Q[0];
  assign result = {salida_A[2],salida_A[1],salida_A[0],salida_Q};

endmodule

// Desplaza_M siempre a 0
// Carga_M y Carga_Q pueden ser iguales porque siempre cargan a la par, A no lo hace 
// A y Q desplazan juntos
// Bit en desplazamiento de q es el bit menos significativo de A
// El c_sumout debería ser bit_en_desp de A?

// reg wire simplemente es implementación interna, cuando lo instanciemos fuera, no pasa nada si lo ponemos en un wire

mul.v
`timescale 1 ns / 10 ps
//module cd(input wire [2:0] multiplicador, input wire [2:0] multiplicando, input wire Carga_A, Carga_QM, Desplaza_AQ, Reset_A, Resta, clk, reset, output wire q0, q_menos1, output wire [5:0] result);
//module uc(input wire q0, reset, clk, q_menos1, output wire Carga_A, Carga_QM, Desplaza_AQ, Reset_A, Resta, Fin);

module multiplicador(input wire [2:0] multiplicando, input wire [2:0] multiplicador, input wire clk, reset, output wire [5:0] result, output wire Fin);
  wire Carga_A, Carga_QM, Desplaza_AQ, Reset_A, Resta, q0, q_menos1;
 
  cd camino(multiplicador, multiplicando, Carga_A, Carga_QM, Desplaza_AQ, Reset_A, Resta, clk, reset, q0, q_menos1, result);   
  uc unidad_control(q0, reset, clk, q_menos1, Carga_A, Carga_QM, Desplaza_AQ, Reset_A, Resta, Fin);

endmodule

multiplicador_tb.v
`timescale 1 ns / 10 ps
module multiplicador_tb;
//Recordar que el caso de -4 en tres bits en el multiplicando dará error en Booth si no hacemos que los registros A y M tengan un bit más (hay overflow) (depende de la implementación del sumador/restador)
parameter NUM_BITS = 2;
parameter NUM_TESTS = (2**(2*NUM_BITS));
parameter MAX_RANGE = (2**(NUM_BITS-1))-1;
parameter MIN_RANGE = - (2**(NUM_BITS-1));
integer contador;
reg clk, start;
wire Fin;
reg signed [NUM_BITS-1:0] multiplicador;
reg signed [NUM_BITS-1:0] multiplicando;
wire [(2*NUM_BITS)-1:0] resultado;
reg signed [(2*NUM_BITS)-1:0] resultado_esperado;

// generación de reloj clk
always //siempre activo, no hay condición de activación
begin
  clk = 1'b0;
  #5;
  clk = 1'b1;
  #5;
end

// Módulo a probar
multiplicador #(NUM_BITS) mult(multiplicando, multiplicador, clk, start, resultado, Fin);

initial
begin
  $dumpfile("multiplicador_tb.vcd");
  $dumpvars;
  #20000   //Evita ejecución infinita
  $finish;
end

//Preparación caso inicial
initial
begin
  multiplicando = MIN_RANGE;
  multiplicador = MIN_RANGE;
  contador = 1;
end 

initial
begin
  start = 1'b1;
  #1;
  start = 1'b0;
end

always @(posedge Fin)
begin
  resultado_esperado = multiplicador * multiplicando;
  //Comprobación de resultados
  $write("%d x %d = %d", multiplicando, multiplicador, resultado_esperado);
  if (resultado !== resultado_esperado)
    $display("\tERROR    Obtenido=%b", resultado);
  else
    $display("\tCORRECTO Obtenido=%b", resultado);
  
  #20  //tiempo de espera entre una multiplicación y la siguiente
  if (contador == NUM_TESTS)
    $finish;
  else //Siguiente caso
  begin
    contador = contador + 1;
    if (multiplicador == MAX_RANGE)
    begin
      multiplicador = MIN_RANGE;
      multiplicando = multiplicando + 1;
    end
    else
    begin
      multiplicador = multiplicador + 1;
    end
    start = 1'b1;
    #1;
    start = 1'b0;           
  end
end

endmodule

multiplicador_tb.vcd
$date
	Wed Feb 24 11:16:52 2021
$end
$version
	Icarus Verilog
$end
$timescale
	10ps
$end
$scope module multiplicador_tb $end
$var wire 6 ! resultado [5:0] $end
$var wire 1 " Fin $end
$var reg 1 # clk $end
$var reg 3 $ multiplicador [2:0] $end
$var reg 3 % multiplicando [2:0] $end
$var reg 6 & resultado_esperado [5:0] $end
$var reg 1 ' start $end
$var integer 32 ( contador [31:0] $end
$scope module mult $end
$var wire 1 # clk $end
$var wire 3 ) multiplicador [2:0] $end
$var wire 3 * multiplicando [2:0] $end
$var wire 1 ' reset $end
$var wire 6 + result [5:0] $end
$var wire 1 , q_menos1 $end
$var wire 1 - q0 $end
$var wire 1 . Resta $end
$var wire 1 / Reset_A $end
$var wire 1 " Fin $end
$var wire 1 0 Desplaza_AQ $end
$var wire 1 1 Carga_QM $end
$var wire 1 2 Carga_A $end
$scope module camino $end
$var wire 1 3 carga_qmenos1 $end
$var wire 1 # clk $end
$var wire 3 4 multiplicador [2:0] $end
$var wire 3 5 multiplicando [2:0] $end
$var wire 1 ' reset $end
$var wire 1 6 reset_qmenos1 $end
$var wire 4 7 salida_sum [3:0] $end
$var wire 3 8 salida_Q [2:0] $end
$var wire 4 9 salida_M [3:0] $end
$var wire 4 : salida_A [3:0] $end
$var wire 6 ; result [5:0] $end
$var wire 1 , q_menos1 $end
$var wire 1 - q0 $end
$var wire 1 < c_sumout $end
$var wire 1 . Resta $end
$var wire 1 / Reset_A $end
$var wire 1 0 Desplaza_AQ $end
$var wire 1 1 Carga_QM $end
$var wire 1 2 Carga_A $end
$scope module A $end
$var wire 1 = bit_en_desp $end
$var wire 1 # clk $end
$var wire 1 > enable $end
$var wire 4 ? salida [3:0] $end
$var wire 1 / reset $end
$var wire 4 @ entrada [3:0] $end
$var wire 1 0 Desplaza $end
$var wire 1 2 Carga $end
$scope module ff0 $end
$var wire 1 > carga $end
$var wire 1 # clk $end
$var wire 1 A inp_c $end
$var wire 1 B inp_d $end
$var wire 1 2 selc_d $end
$var wire 1 C salida $end
$var wire 1 / reset $end
$var wire 1 D inp $end
$scope module ff0 $end
$var wire 1 > carga $end
$var wire 1 # clk $end
$var wire 1 / reset $end
$var wire 1 D d $end
$var reg 1 C q $end
$upscope $end
$scope module mux0 $end
$var wire 1 B a $end
$var wire 1 A b $end
$var wire 1 D out $end
$var wire 1 E s_n $end
$var wire 1 F sa $end
$var wire 1 G sb $end
$var wire 1 2 s $end
$upscope $end
$upscope $end
$scope module ff1 $end
$var wire 1 > carga $end
$var wire 1 # clk $end
$var wire 1 H inp_c $end
$var wire 1 I inp_d $end
$var wire 1 2 selc_d $end
$var wire 1 J salida $end
$var wire 1 / reset $end
$var wire 1 K inp $end
$scope module ff0 $end
$var wire 1 > carga $end
$var wire 1 # clk $end
$var wire 1 / reset $end
$var wire 1 K d $end
$var reg 1 J q $end
$upscope $end
$scope module mux0 $end
$var wire 1 I a $end
$var wire 1 H b $end
$var wire 1 K out $end
$var wire 1 L s_n $end
$var wire 1 M sa $end
$var wire 1 N sb $end
$var wire 1 2 s $end
$upscope $end
$upscope $end
$scope module ff2 $end
$var wire 1 > carga $end
$var wire 1 # clk $end
$var wire 1 O inp_c $end
$var wire 1 P inp_d $end
$var wire 1 2 selc_d $end
$var wire 1 Q salida $end
$var wire 1 / reset $end
$var wire 1 R inp $end
$scope module ff0 $end
$var wire 1 > carga $end
$var wire 1 # clk $end
$var wire 1 / reset $end
$var wire 1 R d $end
$var reg 1 Q q $end
$upscope $end
$scope module mux0 $end
$var wire 1 P a $end
$var wire 1 O b $end
$var wire 1 R out $end
$var wire 1 S s_n $end
$var wire 1 T sa $end
$var wire 1 U sb $end
$var wire 1 2 s $end
$upscope $end
$upscope $end
$scope module ff3 $end
$var wire 1 > carga $end
$var wire 1 # clk $end
$var wire 1 V inp_c $end
$var wire 1 = inp_d $end
$var wire 1 2 selc_d $end
$var wire 1 W salida $end
$var wire 1 / reset $end
$var wire 1 X inp $end
$scope module ff0 $end
$var wire 1 > carga $end
$var wire 1 # clk $end
$var wire 1 / reset $end
$var wire 1 X d $end
$var reg 1 W q $end
$upscope $end
$scope module mux0 $end
$var wire 1 = a $end
$var wire 1 V b $end
$var wire 1 X out $end
$var wire 1 Y s_n $end
$var wire 1 Z sa $end
$var wire 1 [ sb $end
$var wire 1 2 s $end
$upscope $end
$upscope $end
$upscope $end
$scope module M $end
$var wire 1 \ Desplaza $end
$var wire 1 ] bit_en_desp $end
$var wire 1 # clk $end
$var wire 1 ^ enable $end
$var wire 4 _ entrada [3:0] $end
$var wire 1 ' reset $end
$var wire 4 ` salida [3:0] $end
$var wire 1 1 Carga $end
$scope module ff0 $end
$var wire 1 ^ carga $end
$var wire 1 # clk $end
$var wire 1 a inp_c $end
$var wire 1 b inp_d $end
$var wire 1 ' reset $end
$var wire 1 1 selc_d $end
$var wire 1 c salida $end
$var wire 1 d inp $end
$scope module ff0 $end
$var wire 1 ^ carga $end
$var wire 1 # clk $end
$var wire 1 ' reset $end
$var wire 1 d d $end
$var reg 1 c q $end
$upscope $end
$scope module mux0 $end
$var wire 1 b a $end
$var wire 1 a b $end
$var wire 1 d out $end
$var wire 1 e s_n $end
$var wire 1 f sa $end
$var wire 1 g sb $end
$var wire 1 1 s $end
$upscope $end
$upscope $end
$scope module ff1 $end
$var wire 1 ^ carga $end
$var wire 1 # clk $end
$var wire 1 h inp_c $end
$var wire 1 i inp_d $end
$var wire 1 ' reset $end
$var wire 1 1 selc_d $end
$var wire 1 j salida $end
$var wire 1 k inp $end
$scope module ff0 $end
$var wire 1 ^ carga $end
$var wire 1 # clk $end
$var wire 1 ' reset $end
$var wire 1 k d $end
$var reg 1 j q $end
$upscope $end
$scope module mux0 $end
$var wire 1 i a $end
$var wire 1 h b $end
$var wire 1 k out $end
$var wire 1 l s_n $end
$var wire 1 m sa $end
$var wire 1 n sb $end
$var wire 1 1 s $end
$upscope $end
$upscope $end
$scope module ff2 $end
$var wire 1 ^ carga $end
$var wire 1 # clk $end
$var wire 1 o inp_c $end
$var wire 1 p inp_d $end
$var wire 1 ' reset $end
$var wire 1 1 selc_d $end
$var wire 1 q salida $end
$var wire 1 r inp $end
$scope module ff0 $end
$var wire 1 ^ carga $end
$var wire 1 # clk $end
$var wire 1 ' reset $end
$var wire 1 r d $end
$var reg 1 q q $end
$upscope $end
$scope module mux0 $end
$var wire 1 p a $end
$var wire 1 o b $end
$var wire 1 r out $end
$var wire 1 s s_n $end
$var wire 1 t sa $end
$var wire 1 u sb $end
$var wire 1 1 s $end
$upscope $end
$upscope $end
$scope module ff3 $end
$var wire 1 ^ carga $end
$var wire 1 # clk $end
$var wire 1 v inp_c $end
$var wire 1 ] inp_d $end
$var wire 1 ' reset $end
$var wire 1 1 selc_d $end
$var wire 1 w salida $end
$var wire 1 x inp $end
$scope module ff0 $end
$var wire 1 ^ carga $end
$var wire 1 # clk $end
$var wire 1 ' reset $end
$var wire 1 x d $end
$var reg 1 w q $end
$upscope $end
$scope module mux0 $end
$var wire 1 ] a $end
$var wire 1 v b $end
$var wire 1 x out $end
$var wire 1 y s_n $end
$var wire 1 z sa $end
$var wire 1 { sb $end
$var wire 1 1 s $end
$upscope $end
$upscope $end
$upscope $end
$scope module Q $end
$var wire 1 | bit_en_desp $end
$var wire 1 # clk $end
$var wire 1 } enable $end
$var wire 3 ~ entrada [2:0] $end
$var wire 1 ' reset $end
$var wire 3 !" salida [2:0] $end
$var wire 1 0 Desplaza $end
$var wire 1 1 Carga $end
$scope module ff0 $end
$var wire 1 } carga $end
$var wire 1 # clk $end
$var wire 1 "" inp_c $end
$var wire 1 #" inp_d $end
$var wire 1 ' reset $end
$var wire 1 1 selc_d $end
$var wire 1 $" salida $end
$var wire 1 %" inp $end
$scope module ff0 $end
$var wire 1 } carga $end
$var wire 1 # clk $end
$var wire 1 ' reset $end
$var wire 1 %" d $end
$var reg 1 $" q $end
$upscope $end
$scope module mux0 $end
$var wire 1 #" a $end
$var wire 1 "" b $end
$var wire 1 %" out $end
$var wire 1 &" s_n $end
$var wire 1 '" sa $end
$var wire 1 (" sb $end
$var wire 1 1 s $end
$upscope $end
$upscope $end
$scope module ff1 $end
$var wire 1 } carga $end
$var wire 1 # clk $end
$var wire 1 )" inp_c $end
$var wire 1 *" inp_d $end
$var wire 1 ' reset $end
$var wire 1 1 selc_d $end
$var wire 1 +" salida $end
$var wire 1 ," inp $end
$scope module ff0 $end
$var wire 1 } carga $end
$var wire 1 # clk $end
$var wire 1 ' reset $end
$var wire 1 ," d $end
$var reg 1 +" q $end
$upscope $end
$scope module mux0 $end
$var wire 1 *" a $end
$var wire 1 )" b $end
$var wire 1 ," out $end
$var wire 1 -" s_n $end
$var wire 1 ." sa $end
$var wire 1 /" sb $end
$var wire 1 1 s $end
$upscope $end
$upscope $end
$scope module ff2 $end
$var wire 1 } carga $end
$var wire 1 # clk $end
$var wire 1 0" inp_c $end
$var wire 1 | inp_d $end
$var wire 1 ' reset $end
$var wire 1 1 selc_d $end
$var wire 1 1" salida $end
$var wire 1 2" inp $end
$scope module ff0 $end
$var wire 1 } carga $end
$var wire 1 # clk $end
$var wire 1 ' reset $end
$var wire 1 2" d $end
$var reg 1 1" q $end
$upscope $end
$scope module mux0 $end
$var wire 1 | a $end
$var wire 1 0" b $end
$var wire 1 2" out $end
$var wire 1 3" s_n $end
$var wire 1 4" sa $end
$var wire 1 5" sb $end
$var wire 1 1 s $end
$upscope $end
$upscope $end
$upscope $end
$scope module bq_menos1 $end
$var wire 1 # clk $end
$var wire 1 3 d $end
$var wire 1 6 reset $end
$var wire 1 1 carga $end
$var reg 1 , q $end
$upscope $end
$scope module sumador $end
$var wire 4 6" A [3:0] $end
$var wire 4 7" B [3:0] $end
$var wire 1 . resta $end
$var wire 1 < c_out $end
$var wire 4 8" S [3:0] $end
$upscope $end
$upscope $end
$scope module unidad_control $end
$var wire 1 # clk $end
$var wire 1 - q0 $end
$var wire 1 , q_menos1 $end
$var wire 1 ' reset $end
$var wire 1 . Resta $end
$var wire 1 / Reset_A $end
$var wire 1 " Fin $end
$var wire 1 0 Desplaza_AQ $end
$var wire 1 1 Carga_QM $end
$var wire 1 2 Carga_A $end
$var reg 3 9" nextstate [2:0] $end
$var reg 3 :" state [2:0] $end
$upscope $end
$upscope $end
$upscope $end
$enddefinitions $end
#0
$dumpvars
b0 :"
b1 9"
b0 8"
b0 7"
b0 6"
15"
04"
03"
12"
01"
10"
0/"
0."
0-"
0,"
0+"
0*"
0)"
0("
0'"
0&"
0%"
0$"
0#"
0""
b0 !"
b100 ~
1}
0|
1{
0z
0y
1x
0w
1v
1u
0t
0s
1r
0q
0p
1o
0n
0m
0l
0k
0j
0i
0h
0g
0f
0e
0d
0c
0b
0a
b0 `
b1100 _
1^
0]
0\
0[
0Z
1Y
0X
0W
0V
0U
0T
1S
0R
0Q
0P
0O
0N
0M
1L
0K
0J
0I
0H
0G
0F
1E
0D
0C
0B
0A
b0 @
b0 ?
0>
0=
0<
b0 ;
b0 :
b0 9
b0 8
b0 7
z6
b100 5
b100 4
z3
02
11
00
1/
0.
0-
x,
b0 +
b100 *
b100 )
b1 (
1'
bx &
b100 %
b100 $
0#
0"
b0 !
$end
#100
0'
#500
1,"
1k
02"
1."
0x
1t
1m
05"
13"
1-"
1&"
0}
0{
1y
0u
1s
1l
1e
0^
1V
1O
01
0/
b1100 7
b1100 @
b1100 8"
b10 9"
1*"
1p
1i
b1 :"
b100 !
b100 +
b100 ;
b100 8
b100 !"
11"
1w
b1100 9
b1100 `
b1100 7"
1q
z,
1#
#1000
0#
#1500
1}
1>
10
b11 9"
b10 :"
1#
#2000
0#
#2500
0}
0>
00
0,"
1%"
0."
1'"
b100 9"
0*"
1#"
b11 :"
01"
b10 !
b10 +
b10 ;
b10 8
b10 !"
1+"
1#
#3000
0#
#3500
1}
1>
10
b101 9"
b100 :"
1#
#4000
0#
#4500
xV
xX
xR
bx100 7
bx100 @
bx100 8"
x<
x[
xY
xU
xS
xL
xE
0}
x>
x2
00
x.
0%"
0'"
b110 9"
0#"
1-
b101 :"
0+"
b1 !
b1 +
b1 ;
b1 8
b1 !"
1$"
1#
#5000
0#
#5500
1V
0X
0R
b1100 7
b1100 @
b1100 8"
0<
0[
1Y
0U
1S
1L
1E
02
1}
1>
0.
10
b111 9"
b110 :"
1#
#6000
0#
#6500
0}
0>
00
b10000 &
1"
0-
b111 :"
b0 !
b0 +
b0 ;
b0 8
b0 !"
0$"
1#
#7000
0#
#7500
1#
#8000
0#
#8500
12"
1%"
1x
15"
03"
0-"
1("
0&"
1}
1{
0y
1u
0s
0l
0e
1^
1r
0V
0O
0k
11
1/
0"
0t
b0 7
b0 @
b0 8"
0m
b1 9"
0p
0i
b0 :"
0w
b0 9
b0 `
b0 7"
0q
1""
1#
1'
b101 $
b101 )
b101 4
b101 ~
b10 (
#8600
0'
#9000
0#
#9500
xX
xR
x<
x[
xY
xU
xS
xL
xE
x>
x2
1,"
1k
x.
02"
1."
0%"
0x
1t
1m
xV
1O
05"
13"
1-"
0("
1&"
0}
0{
1y
0u
1s
1l
1e
0^
bx100 7
bx100 @
bx100 8"
01
0/
1i
1p
1-
1*"
b10 9"
1q
b1100 9
b1100 `
b1100 7"
1w
1$"
b101 !
b101 +
b101 ;
b101 8
b101 !"
11"
b1 :"
1#
#10000
0#
#10500
1V
0X
0R
b1100 7
b1100 @
b1100 8"
0<
0[
1Y
0U
1S
1L
1E
02
1}
1>
0.
10
b11 9"
b10 :"
1#
#11000
0#
#11500
0}
0>
00
1%"
0,"
1'"
0."
0-
1#"
0*"
b100 9"
0$"
1+"
b10 !
b10 +
b10 ;
b10 8
b10 !"
01"
b11 :"
1#
#12000
0#
#12500
1}
1>
10
b101 9"
b100 :"
1#
#13000
0#
#13500
xV
xX
xR
bx100 7
bx100 @
bx100 8"
x<
x[
xY
xU
xS
xL
xE
x2
x.
0}
x>
00
0%"
0'"
1-
0#"
b110 9"
1$"
b1 !
b1 +
b1 ;
b1 8
b1 !"
0+"
b101 :"
1#
#14000
0#
#14500
1V
0X
0R
b1100 7
b1100 @
b1100 8"
0<
0[
1Y
0U
1S
1L
1E
02
1}
1>
0.
10
b111 9"
b110 :"
1#
#15000
0#
#15500
0}
0>
00
b1100 &
1"
0-
b0 !
b0 +
b0 ;
b0 8
b0 !"
0$"
b111 :"
1#
#16000
0#
#16500
1#
#17000
0#
#17500
12"
1,"
1x
0k
0V
0O
15"
03"
1/"
0-"
0&"
1}
1{
0y
1u
0s
0l
0e
1^
0m
b0 7
b0 @
b0 8"
0t
11
1/
0"
0i
0p
b1 9"
0q
b0 9
b0 `
b0 7"
0w
b0 :"
0""
1)"
1#
1'
b110 $
b110 )
b110 4
b110 ~
b11 (
#17600
0'
#18000
0#
#18500
1%"
1k
02"
1."
1'"
0x
1t
1m
05"
13"
0/"
1-"
1&"
0}
0{
1y
0u
1s
1l
1e
0^
1V
1O
01
0/
b1100 7
b1100 @
b1100 8"
b10 9"
1*"
1#"
1p
1i
b1 :"
11"
b110 !
b110 +
b110 ;
b110 8
b110 !"
1+"
1w
b1100 9
b1100 `
b1100 7"
1q
1#
#19000
0#
#19500
1}
1>
10
b11 9"
b10 :"
1#
#20000
0#
#20500
xV
xX
xR
bx100 7
bx100 @
bx100 8"
x<
x[
xY
xU
xS
xL
xE
0}
x>
x2
x.
00
0,"
0."
b100 9"
0*"
1-
b11 :"
01"
b11 !
b11 +
b11 ;
b11 8
b11 !"
1$"
1#
#21000
0#
#21500
1V
0X
0R
b1100 7
b1100 @
b1100 8"
0<
0[
1Y
0U
1S
1L
1E
02
1}
1>
0.
10
b101 9"
b100 :"
1#
#22000
0#
#22500
xV
xX
xR
bx100 7
bx100 @
bx100 8"
x<
x[
xY
xU
xS
xL
xE
0}
x>
x2
00
x.
0%"
0'"
b110 9"
0#"
b101 :"
b1 !
b1 +
b1 ;
b1 8
b1 !"
0+"
1#
#23000
0#
#23500
1V
0X
0R
b1100 7
b1100 @
b1100 8"
0<
0[
1Y
0U
1S
1L
1E
02
1}
1>
0.
10
b111 9"
b110 :"
1#
#24000
0#
#24500
0}
0>
00
b1000 &
1"
0-
b111 :"
b0 !
b0 +
b0 ;
b0 8
b0 !"
0$"
1#
#25000
0#
#25500
1#
#26000
0#
#26500
12"
1,"
1%"
1x
15"
03"
1/"
0-"
1("
0&"
1}
1{
0y
1u
0s
0l
0e
1^
1r
0V
0O
0k
11
1/
0"
0t
b0 7
b0 @
b0 8"
0m
b1 9"
0p
0i
b0 :"
0w
b0 9
b0 `
b0 7"
0q
1""
1#
1'
b111 $
b111 )
b111 4
b111 ~
b100 (
#26600
0'
#27000
0#
